executables/__init__.py
executables/exe.py
executables/updater.py
mcptool/__init__.py
mcptool/__main__.py
mcptool/banners/__init__.py
mcptool/banners/show_banner.py
mcptool/commands/__init__.py
mcptool/commands/bruteauth.py
mcptool/commands/brutercon.py
mcptool/commands/checker.py
mcptool/commands/clear.py
mcptool/commands/clearservers.py
mcptool/commands/connect.py
mcptool/commands/debug.py
mcptool/commands/discord.py
mcptool/commands/dnslookup.py
mcptool/commands/fakeproxy.py
mcptool/commands/help.py
mcptool/commands/iphistory.py
mcptool/commands/ipinfo.py
mcptool/commands/kick.py
mcptool/commands/kickall.py
mcptool/commands/language.py
mcptool/commands/listening.py
mcptool/commands/password.py
mcptool/commands/proxy.py
mcptool/commands/rcon.py
mcptool/commands/resolver.py
mcptool/commands/scan.py
mcptool/commands/seeker.py
mcptool/commands/sendcmd.py
mcptool/commands/server.py
mcptool/commands/settings.py
mcptool/commands/subdomains.py
mcptool/commands/uuid.py
mcptool/commands/websearch.py
mcptool/commands/arguments/__init__.py
mcptool/commands/arguments/argument_validator.py
mcptool/commands/loader/__init__.py
mcptool/commands/loader/command_loader.py
mcptool/constants/__init__.py
mcptool/constants/banners.py
mcptool/constants/update_available.py
mcptool/dns/__init__.py
mcptool/dns/get_dns_records.py
mcptool/hackertarget/__init__.py
mcptool/hackertarget/get_subdomains.py
mcptool/inputcustom/__init__.py
mcptool/ipv4/__init__.py
mcptool/ipv4/get_cloudflare_ip.py
mcptool/ipv4/get_ip_info.py
mcptool/minecraft/__init__.py
mcptool/minecraft/bot/__init__.py
mcptool/minecraft/bot/server_response.py
mcptool/minecraft/player/__init__.py
mcptool/minecraft/player/get_player_username.py
mcptool/minecraft/player/get_player_uuid.py
mcptool/minecraft/proxy/__init__.py
mcptool/minecraft/proxy/proxy_jar.py
mcptool/minecraft/proxy/start_proxy.py
mcptool/minecraft/server/__init__.py
mcptool/minecraft/server/mcstatus_local.py
mcptool/minecraft/server/mcstatusio_api.py
mcptool_py-1.1.0.dist-info/LICENSE
mcptool_py-1.1.0.dist-info/METADATA
mcptool_py-1.1.0.dist-info/WHEEL
mcptool_py-1.1.0.dist-info/entry_points.txt
mcptool_py-1.1.0.dist-info/top_level.txt
mcptool_py-1.1.0.dist-info/RECORD
