Metadata-Version: 2.1
Name: mcptool-py
Version: 1.1.0
Summary: A tool for Minecraft pentesting
Author-email: "Pedro Agustin Vega (wrrulos)" <pedroagustinvega04@gmail.com>
License: MIT License
Project-URL: homepage, https://mcptool.net
Project-URL: documentation, https://mcptool.net/docs
Project-URL: repository, https://github.com/pedroagustinvega/mcptool
Keywords: minecraft,pentesting,tool,security
Classifier: Programming Language :: Python :: 3
Classifier: License :: OSI Approved :: MIT License
Classifier: Operating System :: OS Independent
Requires-Python: >=3.6
License-File: LICENSE
Requires-Dist: ezjsonpy
Requires-Dist: mccolors
Requires-Dist: mcstatus
Requires-Dist: mcrcon
Requires-Dist: requests
Requires-Dist: loguru
Requires-Dist: pypresence
Requires-Dist: plyer
Requires-Dist: nbtlib
Requires-Dist: bs4
